{
	"animations": [
		{
			"offsets": [
				-55,
				100
			],
			"loop": false,
			"fps": 24,
			"anim": "idle",
			"indices": [],
			"name": "idle"
		},
		{
			"offsets": [
				-69,
				88
			],
			"loop": false,
			"fps": 24,
			"anim": "singDOWN",
			"indices": [],
			"name": "down"
		},
		{
			"offsets": [
				-69,
				167
			],
			"loop": false,
			"fps": 24,
			"anim": "singUP",
			"indices": [],
			"name": "up"
		},
		{
			"offsets": [
				1,
				106
			],
			"loop": true,
			"fps": 24,
			"anim": "singLEFT",
			"indices": [],
			"name": "right"
		},
		{
			"offsets": [
				-101,
				100
			],
			"loop": false,
			"fps": 24,
			"anim": "singRIGHT",
			"indices": [],
			"name": "left"
		}
	],
	"no_antialiasing": false,
	"image": "characters/Realalternate",
	"position": [
		-910,
		240
	],
	"healthicon": "icon-none",
	"flip_x": true,
	"healthbar_colors": [
		235,
		215,
		255
	],
	"camera_position": [
		-40,
		-290
	],
	"sing_duration": 4,
	"scale": 2.2
}